wdxrf/__init__.py
wdxrf/main.py
wdxrf/Layout/__init__.py
wdxrf/Layout/create_button.py
wdxrf/Layout/layouts_style.py
wdxrf/Layout/main_window_att.py
wdxrf/Layout/setting_windows.py
wdxrf/Plot/__init__.py
wdxrf/Plot/frame_attributes.py
wdxrf/Plot/plot_functions.py
wdxrf/Plot/plot_style.py
wdxrf/Plot/utils.py
wdxrf/Processing/__init__.py
wdxrf/Processing/calcul.py
wdxrf/Processing/function_common.py
wdxrf/Processing/xrf.py
xrf2d-1.0.3.dist-info/licenses/LICENSE
xrf2d-1.0.3.dist-info/METADATA
xrf2d-1.0.3.dist-info/WHEEL
xrf2d-1.0.3.dist-info/entry_points.txt
xrf2d-1.0.3.dist-info/top_level.txt
xrf2d-1.0.3.dist-info/RECORD
